pkg_ext/__init__.py
pkg_ext/api_commands.py
pkg_ext/api_dump.py
pkg_ext/changelog.py
pkg_ext/cli.py
pkg_ext/generate.py
pkg_ext/py.typed
pkg_ext/stability.py
pkg_ext/workflows.py
pkg_ext/_internal/__init__.py
pkg_ext/_internal/__main__.py
pkg_ext/_internal/api_diff.py
pkg_ext/_internal/api_dumper.py
pkg_ext/_internal/cli.py
pkg_ext/_internal/config.py
pkg_ext/_internal/context.py
pkg_ext/_internal/errors.py
pkg_ext/_internal/file_parser.py
pkg_ext/_internal/interactive.py
pkg_ext/_internal/pkg_state.py
pkg_ext/_internal/py_format.py
pkg_ext/_internal/settings.py
pkg_ext/_internal/signature_parser.py
pkg_ext/_internal/version_bump.py
pkg_ext/_internal/warnings.py
pkg_ext/_internal/warnings_gen.py
pkg_ext/_internal/changelog/__init__.py
pkg_ext/_internal/changelog/actions.py
pkg_ext/_internal/changelog/committer.py
pkg_ext/_internal/changelog/parser.py
pkg_ext/_internal/changelog/write_changelog_md.py
pkg_ext/_internal/cli/__init__.py
pkg_ext/_internal/cli/api_cmds.py
pkg_ext/_internal/cli/base_commands.py
pkg_ext/_internal/cli/changelog_cmds.py
pkg_ext/_internal/cli/gen_cmds.py
pkg_ext/_internal/cli/options.py
pkg_ext/_internal/cli/stability.py
pkg_ext/_internal/cli/stability_cmds.py
pkg_ext/_internal/cli/workflow_cmds.py
pkg_ext/_internal/cli/workflows.py
pkg_ext/_internal/generation/__init__.py
pkg_ext/_internal/generation/docs.py
pkg_ext/_internal/generation/docs_constants.py
pkg_ext/_internal/generation/docs_mkdocs.py
pkg_ext/_internal/generation/docs_render.py
pkg_ext/_internal/generation/docs_version.py
pkg_ext/_internal/generation/example_gen.py
pkg_ext/_internal/generation/groups.py
pkg_ext/_internal/generation/init_file.py
pkg_ext/_internal/generation/pyproject.py
pkg_ext/_internal/generation/test_gen.py
pkg_ext/_internal/git_usage/__init__.py
pkg_ext/_internal/git_usage/actions.py
pkg_ext/_internal/git_usage/state.py
pkg_ext/_internal/git_usage/url.py
pkg_ext/_internal/models/__init__.py
pkg_ext/_internal/models/api_dump.py
pkg_ext-0.2.1.dist-info/METADATA
pkg_ext-0.2.1.dist-info/WHEEL
pkg_ext-0.2.1.dist-info/entry_points.txt
pkg_ext-0.2.1.dist-info/licenses/LICENSE
pkg_ext-0.2.1.dist-info/RECORD
