Metadata-Version: 2.4
Name: pkg-ext
Version: 0.2.1
Summary: Python package public API management, versioning, and changelog generation
Author-email: EspenAlbert <espen.albert1@gmail.com>
License-Expression: MIT
License-File: LICENSE
Keywords: api,changelog,cli,package-management,versioning
Classifier: Development Status :: 4 - Beta
Classifier: Programming Language :: Python :: 3.13
Requires-Python: >=3.13
Requires-Dist: ask-shell
Requires-Dist: gitpython>=3.1.0
Requires-Dist: model-lib[toml]
Requires-Dist: tomlkit>=0.13
Requires-Dist: zero-3rdparty
